neat_railroad_diagrams/__init__.py
neat_railroad_diagrams/_version.py
neat_railroad_diagrams-0.0.0.dist-info/licenses/LICENSE
neat_railroad_diagrams-0.0.0.dist-info/METADATA
neat_railroad_diagrams-0.0.0.dist-info/WHEEL
neat_railroad_diagrams-0.0.0.dist-info/top_level.txt
neat_railroad_diagrams-0.0.0.dist-info/RECORD
